{
  "pathParameters": {
    "id": "35aefac0-51d3-11e9-9331-17a52abe47f5",
    "locationId": "cfa3d190-507b-11e9-b03b-fd47a97c4034"
  },
  "headers": {
    "userid": "1926fd60-4c49-11e9-a14d-793fbe38ca56"
  },
  "body": {
    "cost": 2,
    "start": 1553829770,
    "end": 1553831584,
    "program": {
      "channel": 432
    },
    "box": {
      "clientAddress": "435.453",
      "locationName": "name",
      "label": "633"
    },
    "location": {
      "id": "43aefac0-51d3-11e9-9331-17a52abe47g1",
      "losantId": "92308409324"
    }
  }
}
