{"status":"success","data":{"id":2161647,"league":{"name":"Spain Liga Primera","abbreviation":"La Liga"},"start":{"local":"2019-10-06T16:00:00","utc":"2019-10-06T14:00:00","epoch":1570370400},"tv_stations":[],"venue":{"name":"Jose Zorrilla","city":"Valladolid","country":{"name":"Spain","abbreviation":"ESP"}},"status":{"period":{"id":1,"name":"1st","unit":"Half","full_name":"1st"},"time":{"minutes":3,"seconds":26,"additionalMinutes":0},"announcedInjuryTime":null,"underReview":false,"name":"In-Progress","id":2,"is_active":true,"defending_team_id":7189},"teams":[{"id":7189,"name":"Valladolid","abbreviation":"REV","location":{"name":"Valladolid","type":"home"},"title":"Valladolid","formation":"442","logo":{"base":"https://cdn-s3.si.com/s3fs-public/teams/soccer/liga/logos/","cuts":{"default":"rev_50.png","50x50":"rev_50.png","100x100":"rev_100.png","100x100_light":"rev_100_stroke.png","360x360":"rev_360.png","250x250":"rev_250.png","150x150":"rev_150.png","40x40":"rev_40.png","40x40_light":"rev_40_stroke.png"}},"color":{"primary":"#000000","secondary":"#ffffff"},"slug":"soccer/team/valladolid","record":{"wins":2,"losses":2,"ties":3,"percentage":".500","points":9},"score":0,"shots":0,"is_winner":false,"linescores":[{"period":{"id":1,"name":"1st","unit":"Half","full_name":"1st"},"score":0,"shots":0},{"period":{"id":2,"name":"2nd","unit":"Half","full_name":"2nd"}}],"leaders":{"goals":{"name":"goals","abbreviation":"G"},"saves":{"name":"saves","abbreviation":"SV"},"assists":{"name":"assists","abbreviation":"A"}}},{"id":6172,"name":"Atletico Madrid","abbreviation":"ATL","location":{"name":"Atletico Madrid","type":"away"},"title":"Atletico Madrid","formation":"442","logo":{"base":"https://cdn-s3.si.com/s3fs-public/teams/soccer/liga/logos/","cuts":{"default":"atl_50.png","50x50":"atl_50.png","100x100":"atl_100.png","100x100_light":"atl_100_stroke.png","360x360":"atl_360.png","250x250":"atl_250.png","150x150":"atl_150.png","40x40":"atl_40.png","40x40_light":"atl_40_stroke.png"}},"color":{"primary":"#13007C","secondary":"#FF0D00"},"slug":"soccer/team/atletico-madrid","record":{"wins":4,"losses":1,"ties":2,"percentage":".714","points":14},"score":0,"shots":0,"is_winner":false,"linescores":[{"period":{"id":1,"name":"1st","unit":"Half","full_name":"1st"},"score":0,"shots":0},{"period":{"id":2,"name":"2nd","unit":"Half","full_name":"2nd"}}],"leaders":{"goals":{"name":"goals","abbreviation":"G"},"saves":{"name":"saves","abbreviation":"SV"},"assists":{"name":"assists","abbreviation":"A"}}}],"last_play":{"period":{"id":1,"name":"1st","unit":"Half","full_name":"1st"},"time":"3:26","text":"Foul"},"scoring_summaries":[],"box_scores":[{"team_id":6172,"team_stats":{"minutes_played":3,"goals":0,"own_goals":0,"assists":0,"shots":{"total":0,"inside_box":0,"outside_box":0,"blocked":0,"shot_result":[{"shot_result_id":null,"name":null,"shots":null,"goals":null}]},"shots_on_goal":0,"shots_on_goal_percentage":0,"saves":0,"crosses":0,"cross_breakdown":{"successful":0,"blocked":0,"percentage":null},"penalty_kicks":{"shots":0,"goals":0},"fouls_committed":1,"fouls_suffered":1,"yellow_cards":0,"red_cards":0,"offsides":1,"corner_kicks":0,"clears":0,"free_kick":1,"throw_ins":0,"wood_work":0,"touches":{"total":6,"passes":1,"passes_attempted":1,"passes_received":1,"passes_missed":0,"pass_completion_percentage":"1.000","interceptions":2,"blocks":0,"pass_length":{"short":0,"long":1},"pass_direction":{"forward":1,"forward_percentage":"1.000","backward":0,"right":1,"left":0},"pass_location":{"own_half":{"total":0,"attempted":0,"percentage":null},"opponent_half":{"total":1,"attempted":1,"percentage":"1.000"}}},"catches":0,"punches":0,"tackles":0,"attacks":{"left":0,"center":0,"right":0,"longball":0},"aerial_duels":{"total":1,"won":1,"percentage":"1.000"},"ground_duels":{"total":0,"won":0,"percentage":null},"possession_percentage":"27","possession_percentage_breakdown":{"field_half":{"own":"50","opponent":"50"},"field_third":{"own":"0","middle":"100","opponent":"0"},"attacking_side":{"left":"0","center":"100","right":"0"}}},"goaltenders":[{"player":{"player_id":572786,"shirt_name":"Oblak","display_name":"Jan Oblak","uniform":"13"},"shots_on_goal_faced":0,"position":{"position_id":1,"name":"Goalkeeper","abbreviation":"GK"},"is_game_started":true,"is_winning_goaltender":null,"is_losing_goaltender":null,"is_tying_goaltender":null,"is_on_pitch":true,"cumulative_record":{"wins":8,"losses":2,"ties":4},"shots_faced":0,"goals_allowed":0,"saves":0,"penalty_kicks":{"shots_faced":0,"goals_allowed":0,"saves":0},"is_shutout":false,"catches":0,"punches":0,"crosses_against":{"total":0,"claimed":0}}],"players":[{"player":{"player_id":572786,"shirt_name":"Oblak","display_name":"Jan Oblak","uniform":"13"},"position":{"position_id":1,"name":"Goalkeeper","abbreviation":"GK"},"is_game_started":true,"minutes_played":3,"goals":0,"own_goals":0,"assists":0,"key_passes":0,"chances_created":0,"shots":0,"shots_on_goal":0,"crosses":0,"cross_breakdown":{"successful":0,"percentage":null},"penalty_kicks":{"shots":0,"goals":0,"won":0},"fouls_committed":0,"fouls_suffered":0,"yellow_cards":0,"red_cards":0,"aerial_duels":{"total":0,"won":0,"percentage":null},"ground_duels":{"total":0,"won":0,"percentage":null},"is_on_pitch":true,"offsides":0,"corner_kicks":0,"clears":0,"goal_mouth_blocks":0,"formation":1,"touches":{"total":0,"passes":0,"completed_passes":0,"passes_received":0,"interceptions":0,"blocks":0},"pass_length":{"short":0,"long":0},"possession_advanced":0,"tackles":0,"average_position":null},{"player":{"player_id":536419,"shirt_name":"Trippier","display_name":"Kieran Trippier","uniform":"23"},"position":{"position_id":4,"name":"Defender","abbreviation":"D"},"is_game_started":true,"minutes_played":3,"goals":0,"own_goals":0,"assists":0,"key_passes":0,"chances_created":0,"shots":0,"shots_on_goal":0,"crosses":0,"cross_breakdown":{"successful":0,"percentage":null},"penalty_kicks":{"shots":0,"goals":0,"won":0},"fouls_committed":0,"fouls_suffered":0,"yellow_cards":0,"red_cards":0,"aerial_duels":{"total":0,"won":0,"percentage":null},"ground_duels":{"total":0,"won":0,"percentage":null},"is_on_pitch":true,"offsides":0,"corner_kicks":0,"clears":0,"goal_mouth_blocks":0,"formation":2,"touches":{"total":0,"passes":0,"completed_passes":0,"passes_received":0,"interceptions":0,"blocks":0},"pass_length":{"short":0,"long":0},"possession_advanced":0,"tackles":0,"average_position":null},{"player":{"player_id":559049,"shirt_name":"Savic","display_name":"Stefan Savic","uniform":"15"},"position":{"position_id":4,"name":"Defender","abbreviation":"D"},"is_game_started":true,"minutes_played":3,"goals":0,"own_goals":0,"assists":0,"key_passes":0,"chances_created":0,"shots":0,"shots_on_goal":0,"crosses":0,"cross_breakdown":{"successful":0,"percentage":null},"penalty_kicks":{"shots":0,"goals":0,"won":0},"fouls_committed":0,"fouls_suffered":0,"yellow_cards":0,"red_cards":0,"aerial_duels":{"total":1,"won":1,"percentage":"1.000"},"ground_duels":{"total":0,"won":0,"percentage":null},"is_on_pitch":true,"offsides":0,"corner_kicks":0,"clears":0,"goal_mouth_blocks":0,"formation":3,"touches":{"total":1,"passes":0,"completed_passes":0,"passes_received":0,"interceptions":0,"blocks":0},"pass_length":{"short":0,"long":0},"possession_advanced":0,"tackles":0,"average_position":"VV21"},{"player":{"player_id":732955,"shirt_name":"Gimenez","display_name":"Jose Gimenez","uniform":"2"},"position":{"position_id":4,"name":"Defender","abbreviation":"D"},"is_game_started":true,"minutes_played":3,"goals":0,"own_goals":0,"assists":0,"key_passes":0,"chances_created":0,"shots":0,"shots_on_goal":0,"crosses":0,"cross_breakdown":{"successful":0,"percentage":null},"penalty_kicks":{"shots":0,"goals":0,"won":0},"fouls_committed":0,"fouls_suffered":0,"yellow_cards":0,"red_cards":0,"aerial_duels":{"total":0,"won":0,"percentage":null},"ground_duels":{"total":0,"won":0,"percentage":null},"is_on_pitch":true,"offsides":0,"corner_kicks":0,"clears":0,"goal_mouth_blocks":0,"formation":4,"touches":{"total":0,"passes":0,"completed_passes":0,"passes_received":0,"interceptions":0,"blocks":0},"pass_length":{"short":0,"long":0},"possession_advanced":0,"tackles":0,"average_position":null},{"player":{"player_id":955562,"shirt_name":"Renan Lodi","display_name":"Renan Lodi","uniform":"12"},"position":{"position_id":4,"name":"Defender","abbreviation":"D"},"is_game_started":true,"minutes_played":3,"goals":0,"own_goals":0,"assists":0,"key_passes":0,"chances_created":0,"shots":0,"shots_on_goal":0,"crosses":0,"cross_breakdown":{"successful":0,"percentage":null},"penalty_kicks":{"shots":0,"goals":0,"won":0},"fouls_committed":0,"fouls_suffered":0,"yellow_cards":0,"red_cards":0,"aerial_duels":{"total":0,"won":0,"percentage":null},"ground_duels":{"total":0,"won":0,"percentage":null},"is_on_pitch":true,"offsides":0,"corner_kicks":0,"clears":0,"goal_mouth_blocks":0,"formation":5,"touches":{"total":0,"passes":0,"completed_passes":0,"passes_received":0,"interceptions":0,"blocks":0},"pass_length":{"short":0,"long":0},"possession_advanced":0,"tackles":0,"average_position":null},{"player":{"player_id":1090700,"shirt_name":"Joao Felix","display_name":"Joao Felix","uniform":"7"},"position":{"position_id":2,"name":"Forward","abbreviation":"F"},"is_game_started":true,"minutes_played":3,"goals":0,"own_goals":0,"assists":0,"key_passes":0,"chances_created":0,"shots":0,"shots_on_goal":0,"crosses":0,"cross_breakdown":{"successful":0,"percentage":null},"penalty_kicks":{"shots":0,"goals":0,"won":0},"fouls_committed":0,"fouls_suffered":0,"yellow_cards":0,"red_cards":0,"aerial_duels":{"total":0,"won":0,"percentage":null},"ground_duels":{"total":0,"won":0,"percentage":null},"is_on_pitch":true,"offsides":0,"corner_kicks":0,"clears":0,"goal_mouth_blocks":0,"formation":6,"touches":{"total":0,"passes":0,"completed_passes":0,"passes_received":0,"interceptions":0,"blocks":0},"pass_length":{"short":0,"long":0},"possession_advanced":0,"tackles":0,"average_position":null},{"player":{"player_id":617760,"shirt_name":"Saul","display_name":"Saul Niguez","uniform":"8"},"position":{"position_id":3,"name":"Midfielder","abbreviation":"M"},"is_game_started":true,"minutes_played":3,"goals":0,"own_goals":0,"assists":0,"key_passes":0,"chances_created":0,"shots":0,"shots_on_goal":0,"crosses":0,"cross_breakdown":{"successful":0,"percentage":null},"penalty_kicks":{"shots":0,"goals":0,"won":0},"fouls_committed":0,"fouls_suffered":0,"yellow_cards":0,"red_cards":0,"aerial_duels":{"total":0,"won":0,"percentage":null},"ground_duels":{"total":0,"won":0,"percentage":null},"is_on_pitch":true,"offsides":0,"corner_kicks":0,"clears":0,"goal_mouth_blocks":0,"formation":7,"touches":{"total":0,"passes":0,"completed_passes":0,"passes_received":0,"interceptions":0,"blocks":0},"pass_length":{"short":0,"long":0},"possession_advanced":0,"tackles":0,"average_position":null},{"player":{"player_id":727718,"shirt_name":"Thomas","display_name":"Thomas Partey","uniform":"5"},"position":{"position_id":3,"name":"Midfielder","abbreviation":"M"},"is_game_started":true,"minutes_played":3,"goals":0,"own_goals":0,"assists":0,"key_passes":0,"chances_created":0,"shots":0,"shots_on_goal":0,"crosses":0,"cross_breakdown":{"successful":0,"percentage":null},"penalty_kicks":{"shots":0,"goals":0,"won":0},"fouls_committed":0,"fouls_suffered":0,"yellow_cards":0,"red_cards":0,"aerial_duels":{"total":0,"won":0,"percentage":null},"ground_duels":{"total":0,"won":0,"percentage":null},"is_on_pitch":true,"offsides":0,"corner_kicks":0,"clears":0,"goal_mouth_blocks":0,"formation":8,"touches":{"total":1,"passes":0,"completed_passes":0,"passes_received":0,"interceptions":0,"blocks":0},"pass_length":{"short":0,"long":0},"possession_advanced":0,"tackles":0,"average_position":"VT24"},{"player":{"player_id":515035,"shirt_name":"Koke","display_name":"Koke","uniform":"6"},"position":{"position_id":3,"name":"Midfielder","abbreviation":"M"},"is_game_started":true,"minutes_played":3,"goals":0,"own_goals":0,"assists":0,"key_passes":0,"chances_created":0,"shots":0,"shots_on_goal":0,"crosses":0,"cross_breakdown":{"successful":0,"percentage":null},"penalty_kicks":{"shots":0,"goals":0,"won":0},"fouls_committed":0,"fouls_suffered":0,"yellow_cards":0,"red_cards":0,"aerial_duels":{"total":0,"won":0,"percentage":null},"ground_duels":{"total":0,"won":0,"percentage":null},"is_on_pitch":true,"offsides":0,"corner_kicks":0,"clears":0,"goal_mouth_blocks":0,"formation":9,"touches":{"total":2,"passes":1,"completed_passes":1,"passes_received":0,"completion_percentage":"1.000","interceptions":1,"blocks":0},"pass_length":{"short":0,"long":1},"possession_advanced":6,"tackles":0,"average_position":"VN24"},{"player":{"player_id":581240,"shirt_name":"Morata","display_name":"Alvaro Morata","uniform":"9"},"position":{"position_id":2,"name":"Forward","abbreviation":"F"},"is_game_started":true,"minutes_played":3,"goals":0,"own_goals":0,"assists":0,"key_passes":0,"chances_created":0,"shots":0,"shots_on_goal":0,"crosses":0,"cross_breakdown":{"successful":0,"percentage":null},"penalty_kicks":{"shots":0,"goals":0},"fouls_committed":0,"fouls_suffered":1,"yellow_cards":0,"red_cards":0,"aerial_duels":{"total":0,"won":0,"percentage":null},"ground_duels":{"total":0,"won":0,"percentage":null},"is_on_pitch":true,"offsides":0,"corner_kicks":0,"clears":0,"goal_mouth_blocks":0,"formation":10,"touches":{"total":0,"passes":0,"completed_passes":0,"passes_received":1,"interceptions":0,"blocks":0},"pass_length":{"short":0,"long":0},"possession_advanced":6,"tackles":0,"average_position":"HH19"},{"player":{"player_id":377080,"shirt_name":"Diego Costa","display_name":"Diego Costa","uniform":"19"},"position":{"position_id":2,"name":"Forward","abbreviation":"F"},"is_game_started":true,"minutes_played":3,"goals":0,"own_goals":0,"assists":0,"key_passes":0,"chances_created":0,"shots":0,"shots_on_goal":0,"crosses":0,"cross_breakdown":{"successful":0,"percentage":null},"penalty_kicks":{"shots":0,"goals":0,"won":0},"fouls_committed":0,"fouls_suffered":0,"yellow_cards":0,"red_cards":0,"aerial_duels":{"total":0,"won":0,"percentage":null},"ground_duels":{"total":0,"won":0,"percentage":null},"is_on_pitch":true,"offsides":1,"corner_kicks":0,"clears":0,"goal_mouth_blocks":0,"formation":11,"touches":{"total":1,"passes":0,"completed_passes":0,"passes_received":0,"interceptions":1,"blocks":0},"pass_length":{"short":0,"long":0},"possession_advanced":0,"tackles":0,"average_position":"HO18"}],"bench_players":[{"player":{"player_id":388415,"shirt_name":"Adan","display_name":"Antonio Adan","uniform":"1"},"yellow_cards":0,"red_cards":0},{"player":{"player_id":727332,"shirt_name":"Correa","display_name":"Angel Correa","uniform":"10"},"yellow_cards":0,"red_cards":0},{"player":{"player_id":860203,"shirt_name":"Llorente","display_name":"Marcos Llorente","uniform":"14"},"yellow_cards":0,"red_cards":0},{"player":{"player_id":749748,"shirt_name":"Lemar","display_name":"Thomas Lemar","uniform":"11"},"yellow_cards":0,"red_cards":0},{"player":{"player_id":716865,"shirt_name":"Arias","display_name":"Santiago Arias","uniform":"4"},"yellow_cards":0,"red_cards":0},{"player":{"player_id":657183,"shirt_name":"Felipe","display_name":"Felipe","uniform":"18"},"yellow_cards":0,"red_cards":0},{"player":{"player_id":492556,"shirt_name":"Herrera","display_name":"Hector Herrera","uniform":"16"},"yellow_cards":0,"red_cards":0}]},{"team_id":7189,"team_stats":{"minutes_played":3,"goals":0,"own_goals":0,"assists":0,"shots":{"total":0,"inside_box":0,"outside_box":0,"blocked":0,"shot_result":[{"shot_result_id":null,"name":null,"shots":null,"goals":null}]},"shots_on_goal":0,"shots_on_goal_percentage":0,"saves":0,"crosses":0,"cross_breakdown":{"successful":0,"blocked":0,"percentage":null},"penalty_kicks":{"shots":0,"goals":0},"fouls_committed":1,"fouls_suffered":1,"yellow_cards":1,"red_cards":0,"offsides":0,"corner_kicks":0,"clears":0,"free_kick":1,"throw_ins":0,"wood_work":0,"touches":{"total":16,"passes":13,"passes_attempted":16,"passes_received":13,"passes_missed":3,"pass_completion_percentage":".813","interceptions":0,"blocks":0,"pass_length":{"short":1,"long":12},"pass_direction":{"forward":4,"forward_percentage":".364","backward":7,"right":7,"left":5},"pass_location":{"own_half":{"total":13,"attempted":15,"percentage":".867"},"opponent_half":{"total":0,"attempted":1,"percentage":".000"}}},"catches":0,"punches":0,"tackles":0,"attacks":{"left":0,"center":0,"right":0,"longball":0},"aerial_duels":{"total":1,"won":0,"percentage":".000"},"ground_duels":{"total":0,"won":0,"percentage":null},"possession_percentage":"73","possession_percentage_breakdown":{"field_half":{"own":"100","opponent":"0"},"field_third":{"own":"69","middle":"31","opponent":"0"},"attacking_side":{"left":null,"center":null,"right":null}}},"goaltenders":[{"player":{"player_id":564644,"shirt_name":"Masip","display_name":"Jordi Masip","uniform":"1"},"shots_on_goal_faced":0,"position":{"position_id":1,"name":"Goalkeeper","abbreviation":"GK"},"is_game_started":true,"is_winning_goaltender":null,"is_losing_goaltender":null,"is_tying_goaltender":null,"is_on_pitch":true,"cumulative_record":{"wins":4,"losses":4,"ties":6},"shots_faced":0,"goals_allowed":0,"saves":0,"penalty_kicks":{"shots_faced":0,"goals_allowed":0,"saves":0},"is_shutout":false,"catches":0,"punches":0,"crosses_against":{"total":0,"claimed":0}}],"players":[{"player":{"player_id":564644,"shirt_name":"Masip","display_name":"Jordi Masip","uniform":"1"},"position":{"position_id":1,"name":"Goalkeeper","abbreviation":"GK"},"is_game_started":true,"minutes_played":3,"goals":0,"own_goals":0,"assists":0,"key_passes":0,"chances_created":0,"shots":0,"shots_on_goal":0,"crosses":0,"cross_breakdown":{"successful":0,"percentage":null},"penalty_kicks":{"shots":0,"goals":0,"won":0},"fouls_committed":0,"fouls_suffered":0,"yellow_cards":0,"red_cards":0,"aerial_duels":{"total":0,"won":0,"percentage":null},"ground_duels":{"total":0,"won":0,"percentage":null},"is_on_pitch":true,"offsides":0,"corner_kicks":0,"clears":0,"goal_mouth_blocks":0,"formation":1,"touches":{"total":2,"passes":2,"completed_passes":2,"passes_received":2,"completion_percentage":"1.000","interceptions":0,"blocks":0},"pass_length":{"short":0,"long":2},"possession_advanced":-6,"tackles":0,"average_position":"HJ6"},{"player":{"player_id":740090,"shirt_name":"Moyano","display_name":"Javi Moyano","uniform":"17"},"position":{"position_id":4,"name":"Defender","abbreviation":"D"},"is_game_started":true,"minutes_played":3,"goals":0,"own_goals":0,"assists":0,"key_passes":0,"chances_created":0,"shots":0,"shots_on_goal":0,"crosses":0,"cross_breakdown":{"successful":0,"percentage":null},"penalty_kicks":{"shots":0,"goals":0,"won":0},"fouls_committed":0,"fouls_suffered":0,"yellow_cards":0,"red_cards":0,"aerial_duels":{"total":0,"won":0,"percentage":null},"ground_duels":{"total":0,"won":0,"percentage":null},"is_on_pitch":true,"offsides":0,"corner_kicks":0,"clears":0,"goal_mouth_blocks":0,"formation":2,"touches":{"total":1,"passes":1,"completed_passes":1,"passes_received":1,"completion_percentage":"1.000","interceptions":0,"blocks":0},"pass_length":{"short":0,"long":1},"possession_advanced":5,"tackles":0,"average_position":"HX12"},{"player":{"player_id":487988,"shirt_name":"Kiko","display_name":"Kiko Olivas","uniform":"4"},"position":{"position_id":4,"name":"Defender","abbreviation":"D"},"is_game_started":true,"minutes_played":3,"goals":0,"own_goals":0,"assists":0,"key_passes":0,"chances_created":0,"shots":0,"shots_on_goal":0,"crosses":0,"cross_breakdown":{"successful":0,"percentage":null},"penalty_kicks":{"shots":0,"goals":0,"won":0},"fouls_committed":0,"fouls_suffered":0,"yellow_cards":0,"red_cards":0,"aerial_duels":{"total":0,"won":0,"percentage":null},"ground_duels":{"total":0,"won":0,"percentage":null},"is_on_pitch":true,"offsides":0,"corner_kicks":0,"clears":0,"goal_mouth_blocks":0,"formation":3,"touches":{"total":3,"passes":3,"completed_passes":2,"passes_received":2,"completion_percentage":".667","interceptions":0,"blocks":0},"pass_length":{"short":1,"long":1},"possession_advanced":-22,"tackles":0,"average_position":"HT16"},{"player":{"player_id":1126641,"shirt_name":"Salisu","display_name":"Mohammed Salisu","uniform":"27"},"position":{"position_id":4,"name":"Defender","abbreviation":"D"},"is_game_started":true,"minutes_played":3,"goals":0,"own_goals":0,"assists":0,"key_passes":0,"chances_created":0,"shots":0,"shots_on_goal":0,"crosses":0,"cross_breakdown":{"successful":0,"percentage":null},"penalty_kicks":{"shots":0,"goals":0,"won":0},"fouls_committed":0,"fouls_suffered":0,"yellow_cards":0,"red_cards":0,"aerial_duels":{"total":0,"won":0,"percentage":null},"ground_duels":{"total":0,"won":0,"percentage":null},"is_on_pitch":true,"offsides":0,"corner_kicks":0,"clears":0,"goal_mouth_blocks":0,"formation":4,"touches":{"total":2,"passes":2,"completed_passes":1,"passes_received":2,"completion_percentage":".500","interceptions":0,"blocks":0},"pass_length":{"short":0,"long":1},"possession_advanced":-8,"tackles":0,"average_position":"HF13"},{"player":{"player_id":716993,"shirt_name":"Martinez","display_name":"Nacho Martinez","uniform":"22"},"position":{"position_id":4,"name":"Defender","abbreviation":"D"},"is_game_started":true,"minutes_played":3,"goals":0,"own_goals":0,"assists":0,"key_passes":0,"chances_created":0,"shots":0,"shots_on_goal":0,"crosses":0,"cross_breakdown":{"successful":0,"percentage":null},"penalty_kicks":{"shots":0,"goals":0,"won":0},"fouls_committed":1,"fouls_suffered":0,"yellow_cards":1,"red_cards":0,"aerial_duels":{"total":0,"won":0,"percentage":null},"ground_duels":{"total":0,"won":0,"percentage":null},"is_on_pitch":true,"offsides":0,"corner_kicks":0,"clears":0,"goal_mouth_blocks":0,"formation":5,"touches":{"total":1,"passes":1,"completed_passes":1,"passes_received":1,"completion_percentage":"1.000","interceptions":0,"blocks":0},"pass_length":{"short":0,"long":1},"possession_advanced":11,"tackles":0,"average_position":"HH15"},{"player":{"player_id":615581,"shirt_name":"Plano","display_name":"Oscar Plano","uniform":"10"},"position":{"position_id":3,"name":"Midfielder","abbreviation":"M"},"is_game_started":true,"minutes_played":3,"goals":0,"own_goals":0,"assists":0,"key_passes":0,"chances_created":0,"shots":0,"shots_on_goal":0,"crosses":0,"cross_breakdown":{"successful":0,"percentage":null},"penalty_kicks":{"shots":0,"goals":0,"won":0},"fouls_committed":0,"fouls_suffered":0,"yellow_cards":0,"red_cards":0,"aerial_duels":{"total":0,"won":0,"percentage":null},"ground_duels":{"total":0,"won":0,"percentage":null},"is_on_pitch":true,"offsides":0,"corner_kicks":0,"clears":0,"goal_mouth_blocks":0,"formation":6,"touches":{"total":1,"passes":1,"completed_passes":0,"passes_received":1,"completion_percentage":".000","interceptions":0,"blocks":0},"pass_length":{"short":0,"long":0},"possession_advanced":-1,"tackles":0,"average_position":"HY24"},{"player":{"player_id":486820,"shirt_name":"Michel","display_name":"Michel","uniform":"21"},"position":{"position_id":3,"name":"Midfielder","abbreviation":"M"},"is_game_started":true,"minutes_played":3,"goals":0,"own_goals":0,"assists":0,"key_passes":0,"chances_created":0,"shots":0,"shots_on_goal":0,"crosses":0,"cross_breakdown":{"successful":0,"percentage":null},"penalty_kicks":{"shots":0,"goals":0,"won":0},"fouls_committed":0,"fouls_suffered":0,"yellow_cards":0,"red_cards":0,"aerial_duels":{"total":0,"won":0,"percentage":null},"ground_duels":{"total":0,"won":0,"percentage":null},"is_on_pitch":true,"offsides":0,"corner_kicks":0,"clears":0,"goal_mouth_blocks":0,"formation":7,"touches":{"total":3,"passes":3,"completed_passes":3,"passes_received":3,"completion_percentage":"1.000","interceptions":0,"blocks":0},"pass_length":{"short":0,"long":3},"possession_advanced":-7,"tackles":0,"average_position":"HM20"},{"player":{"player_id":897493,"shirt_name":"Fernandez","display_name":"Joaquin Fernandez","uniform":"24"},"position":{"position_id":4,"name":"Defender","abbreviation":"D"},"is_game_started":true,"minutes_played":3,"goals":0,"own_goals":0,"assists":0,"key_passes":0,"chances_created":0,"shots":0,"shots_on_goal":0,"crosses":0,"cross_breakdown":{"successful":0,"percentage":null},"penalty_kicks":{"shots":0,"goals":0,"won":0},"fouls_committed":0,"fouls_suffered":0,"yellow_cards":0,"red_cards":0,"aerial_duels":{"total":0,"won":0,"percentage":null},"ground_duels":{"total":0,"won":0,"percentage":null},"is_on_pitch":true,"offsides":0,"corner_kicks":0,"clears":0,"goal_mouth_blocks":0,"formation":8,"touches":{"total":2,"passes":2,"completed_passes":2,"passes_received":1,"completion_percentage":"1.000","interceptions":0,"blocks":0},"pass_length":{"short":0,"long":2},"possession_advanced":-9,"tackles":0,"average_position":"HM18"},{"player":{"player_id":892919,"shirt_name":"Villa","display_name":"Toni Villa","uniform":"19"},"position":{"position_id":3,"name":"Midfielder","abbreviation":"M"},"is_game_started":true,"minutes_played":3,"goals":0,"own_goals":0,"assists":0,"key_passes":0,"chances_created":0,"shots":0,"shots_on_goal":0,"crosses":0,"cross_breakdown":{"successful":0,"percentage":null},"penalty_kicks":{"shots":0,"goals":0,"won":0},"fouls_committed":0,"fouls_suffered":0,"yellow_cards":0,"red_cards":0,"aerial_duels":{"total":0,"won":0,"percentage":null},"ground_duels":{"total":0,"won":0,"percentage":null},"is_on_pitch":true,"offsides":0,"corner_kicks":0,"clears":0,"goal_mouth_blocks":0,"formation":9,"touches":{"total":0,"passes":0,"completed_passes":0,"passes_received":0,"interceptions":0,"blocks":0},"pass_length":{"short":0,"long":0},"possession_advanced":0,"tackles":0,"average_position":null},{"player":{"player_id":846071,"shirt_name":"Guardiola","display_name":"Sergi Guardiola","uniform":"7"},"position":{"position_id":2,"name":"Forward","abbreviation":"F"},"is_game_started":true,"minutes_played":3,"goals":0,"own_goals":0,"assists":0,"key_passes":0,"chances_created":0,"shots":0,"shots_on_goal":0,"crosses":0,"cross_breakdown":{"successful":0,"percentage":null},"penalty_kicks":{"shots":0,"goals":0,"won":0},"fouls_committed":0,"fouls_suffered":0,"yellow_cards":0,"red_cards":0,"aerial_duels":{"total":1,"won":0,"percentage":".000"},"ground_duels":{"total":0,"won":0,"percentage":null},"is_on_pitch":true,"offsides":0,"corner_kicks":0,"clears":0,"goal_mouth_blocks":0,"formation":10,"touches":{"total":1,"passes":1,"completed_passes":1,"passes_received":0,"completion_percentage":"1.000","interceptions":0,"blocks":0},"pass_length":{"short":0,"long":1},"possession_advanced":-8,"tackles":0,"average_position":"VR24"},{"player":{"player_id":740311,"shirt_name":"Sandro","display_name":"Sandro Ramirez","uniform":"20"},"position":{"position_id":2,"name":"Forward","abbreviation":"F"},"is_game_started":true,"minutes_played":3,"goals":0,"own_goals":0,"assists":0,"key_passes":0,"chances_created":0,"shots":0,"shots_on_goal":0,"crosses":0,"cross_breakdown":{"successful":0,"percentage":null},"penalty_kicks":{"shots":0,"goals":0,"won":0},"fouls_committed":0,"fouls_suffered":0,"yellow_cards":0,"red_cards":0,"aerial_duels":{"total":0,"won":0,"percentage":null},"ground_duels":{"total":0,"won":0,"percentage":null},"is_on_pitch":true,"offsides":0,"corner_kicks":0,"clears":0,"goal_mouth_blocks":0,"formation":11,"touches":{"total":0,"passes":0,"completed_passes":0,"passes_received":0,"interceptions":0,"blocks":0},"pass_length":{"short":0,"long":0},"possession_advanced":0,"tackles":0,"average_position":null}],"bench_players":[{"player":{"player_id":1054396,"shirt_name":"Lunin","display_name":"Andriy Lunin","uniform":"13"},"yellow_cards":0,"red_cards":0},{"player":{"player_id":1096461,"shirt_name":"Rubio","display_name":"Waldo Rubio","uniform":"23"},"yellow_cards":0,"red_cards":0},{"player":{"player_id":719378,"shirt_name":"Pablo Hervias","display_name":"Pablo Hervias","uniform":"11"},"yellow_cards":0,"red_cards":0},{"player":{"player_id":846950,"shirt_name":"Anuar","display_name":"Anuar","uniform":"8"},"yellow_cards":0,"red_cards":0},{"player":{"player_id":786963,"shirt_name":"El Hacen","display_name":"El Hacen","uniform":"33"},"yellow_cards":0,"red_cards":0},{"player":{"player_id":750543,"shirt_name":"Unal","display_name":"Enes Unal","uniform":"9"},"yellow_cards":0,"red_cards":0},{"player":{"player_id":484512,"shirt_name":"Antonito","display_name":"Antonito","uniform":"18"},"yellow_cards":0,"red_cards":0}],"cards":[{"time":"2:26","minutes":2,"color":"yellow","player":{"playerId":716993,"shirtName":"Martinez","displayName":"Nacho Martinez","uniform":"22"},"reason":{"bookingReasonId":27,"name":"Tactical Foul"}}]}],"play_by_play":[{"period":{"id":1,"name":"1st","unit":"Half","full_name":"1st"},"time":"1:00","sequence_number":6,"play_event":{"play_event_id":21,"name":"Start Half"},"team_id":7189,"away_score":0,"home_score":0,"away_shootout_score":null,"home_shootout_score":null,"field_coordinates":{"x":null,"y":null},"play_text":"1st Half started","key_moment_sequence_number":null,"defending_x_zero_team_id":7189},{"period":{"id":1,"name":"1st","unit":"Half","full_name":"1st"},"time":"1:30","sequence_number":39,"play_event":{"play_event_id":16,"name":"Offside"},"team_id":6172,"away_score":0,"home_score":0,"away_shootout_score":null,"home_shootout_score":null,"offensive_player":{"player_id":377080,"shirt_name":"Diego Costa","display_name":"Diego Costa","uniform":"19"},"field_coordinates":{"x":33,"y":30},"play_text":"Offsides called on Diego Costa","key_moment_sequence_number":null,"defending_x_zero_team_id":7189},{"period":{"id":1,"name":"1st","unit":"Half","full_name":"1st"},"time":"1:40","sequence_number":41,"play_event":{"play_event_id":9,"name":"Free Kick"},"team_id":7189,"away_score":0,"home_score":0,"away_shootout_score":null,"home_shootout_score":null,"offensive_player":{"player_id":487988,"shirt_name":"Kiko","display_name":"Kiko Olivas","uniform":"4"},"field_coordinates":{"x":32,"y":35},"play_text":"Free kick taken by Kiko Olivas resulting in Pass","free_kick_result":{"free_kick_result_id":2,"name":"Pass"},"key_moment_sequence_number":null,"defending_x_zero_team_id":7189},{"period":{"id":1,"name":"1st","unit":"Half","full_name":"1st"},"time":"2:20","sequence_number":81,"play_event":{"play_event_id":8,"name":"Foul"},"team_id":7189,"away_score":0,"home_score":0,"away_shootout_score":null,"home_shootout_score":null,"offensive_player":{"player_id":716993,"shirt_name":"Martinez","display_name":"Nacho Martinez","uniform":"22"},"defensive_player":{"player_id":581240,"shirt_name":"Morata","display_name":"Alvaro Morata","uniform":"9"},"field_coordinates":{"x":33,"y":20},"play_text":"Foul called on Nacho Martinez","foul_type":{"foul_type_id":1,"name":"Foul"},"key_moment_sequence_number":null,"defending_x_zero_team_id":7189},{"period":{"id":1,"name":"1st","unit":"Half","full_name":"1st"},"time":"2:26","sequence_number":87,"play_event":{"play_event_id":2,"name":"Caution"},"team_id":7189,"away_score":0,"home_score":0,"away_shootout_score":null,"home_shootout_score":null,"offensive_player":{"player_id":716993,"shirt_name":"Martinez","display_name":"Nacho Martinez","uniform":"22"},"field_coordinates":{"x":null,"y":null},"play_text":"Yellow card given to Nacho Martinez (Tactical Foul)","booking_reason":{"booking_reason_id":27,"name":"Tactical Foul"},"key_moment_sequence_number":null,"defending_x_zero_team_id":7189},{"period":{"id":1,"name":"1st","unit":"Half","full_name":"1st"},"time":"3:22","sequence_number":108,"play_event":{"play_event_id":9,"name":"Free Kick"},"team_id":6172,"away_score":0,"home_score":0,"away_shootout_score":null,"home_shootout_score":null,"field_coordinates":{"x":null,"y":null},"play_text":"Free kick","key_moment_sequence_number":null,"defending_x_zero_team_id":7189},{"period":{"id":1,"name":"1st","unit":"Half","full_name":"1st"},"time":"3:26","sequence_number":112,"play_event":{"play_event_id":8,"name":"Foul"},"team_id":6172,"away_score":0,"home_score":0,"away_shootout_score":null,"home_shootout_score":null,"field_coordinates":{"x":null,"y":null},"play_text":"Foul","key_moment_sequence_number":null,"defending_x_zero_team_id":7189}],"links":[{"name":"Recap","url":"https://www.si.com/liga/game/2161647","id":1},{"name":"Box Score","url":"https://www.si.com/liga/game/2161647/box-score","id":2},{"name":"Play-by-Play","url":"https://www.si.com/liga/game/2161647/play-by-play","id":3}],"recent":{"REV":[{"id":2161620,"event_type":{"id":"1","name":"Regular Season"},"league":{"name":"Spain Liga Primera","abbreviation":"La Liga"},"start":{"local":"2019-09-29T12:00:00","utc":"2019-09-29T10:00:00","epoch":"1569751200"},"venue":{"city":"Cornella de Llobregat","venueId":8837,"name":"RCDE Stadium","country":{"abbreviation":"ESP","name":"Spain"}},"status":{"name":"Final","id":4,"is_active":false},"teams":[{"id":6178,"name":"Espanyol","abbreviation":"ESP","location":{"name":"Espanyol","type":"home"},"title":"Espanyol","logo":{"base":"https://cdn-s3.si.com/s3fs-public/teams/soccer/liga/logos/","cuts":{"default":"esp_50.png","50x50":"esp_50.png","100x100":"esp_100.png","100x100_light":"esp_100_stroke.png","360x360":"esp_360.png","250x250":"esp_250.png","150x150":"esp_150.png","40x40":"esp_40.png","40x40_light":"esp_40_stroke.png"}},"color":{"primary":"#000000","secondary":"#FF1119"},"slug":"soccer/team/espanyol","record":{"wins":1,"percentage":".286","losses":4,"ties":2,"points":5},"score":0,"is_winner":false,"linescores":[{"score":0,"period":{"id":1,"name":"1st","unit":"Half","full_name":"1st"},"shots":5},{"score":0,"period":{"id":2,"name":"2nd","unit":"Half","full_name":"2nd"},"shots":11}]},{"id":"7189","name":"Valladolid","abbreviation":"REV","location":{"name":"Valladolid","type":"away"},"title":"Valladolid","logo":{"base":"https://cdn-s3.si.com/s3fs-public/teams/soccer/liga/logos/","cuts":{"default":"rev_50.png","50x50":"rev_50.png","100x100":"rev_100.png","100x100_light":"rev_100_stroke.png","360x360":"rev_360.png","250x250":"rev_250.png","150x150":"rev_150.png","40x40":"rev_40.png","40x40_light":"rev_40_stroke.png"}},"color":{"primary":"#000000","secondary":"#ffffff"},"slug":"soccer/team/valladolid","record":{"wins":2,"percentage":".500","losses":2,"ties":3,"points":9},"score":2,"is_winner":true,"linescores":[{"score":1,"period":{"id":1,"name":"1st","unit":"Half","full_name":"1st"},"shots":6},{"score":1,"period":{"id":2,"name":"2nd","unit":"Half","full_name":"2nd"},"shots":3}]}]},{"id":2161611,"event_type":{"id":"1","name":"Regular Season"},"league":{"name":"Spain Liga Primera","abbreviation":"La Liga"},"start":{"local":"2019-09-24T19:00:00","utc":"2019-09-24T17:00:00","epoch":"1569344400"},"venue":{"city":"Valladolid","venueId":5277,"name":"Jose Zorrilla","country":{"abbreviation":"ESP","name":"Spain"}},"status":{"name":"Final","id":4,"is_active":false},"teams":[{"id":7189,"name":"Valladolid","abbreviation":"REV","location":{"name":"Valladolid","type":"home"},"title":"Valladolid","logo":{"base":"https://cdn-s3.si.com/s3fs-public/teams/soccer/liga/logos/","cuts":{"default":"rev_50.png","50x50":"rev_50.png","100x100":"rev_100.png","100x100_light":"rev_100_stroke.png","360x360":"rev_360.png","250x250":"rev_250.png","150x150":"rev_150.png","40x40":"rev_40.png","40x40_light":"rev_40_stroke.png"}},"color":{"primary":"#000000","secondary":"#ffffff"},"slug":"soccer/team/valladolid","record":{"wins":1,"percentage":".417","losses":2,"ties":3,"points":6},"score":1,"is_winner":false,"linescores":[{"score":1,"period":{"id":1,"name":"1st","unit":"Half","full_name":"1st"},"shots":2},{"score":0,"period":{"id":2,"name":"2nd","unit":"Half","full_name":"2nd"},"shots":7}]},{"id":"23420","name":"Granada","abbreviation":"GRA","location":{"name":"Granada","type":"away"},"title":"Granada","logo":{"base":"https://cdn-s3.si.com/s3fs-public/teams/soccer/liga/logos/","cuts":{"default":"gra_50.png","50x50":"gra_50.png","100x100":"gra_100.png","100x100_light":"gra_100_stroke.png","360x360":"gra_360.png","250x250":"gra_250.png","150x150":"gra_150.png","40x40":"gra_40.png","40x40_light":"gra_40_stroke.png"}},"color":{"primary":"#000000","secondary":"#ffffff"},"slug":"soccer/team/granada","record":{"wins":3,"percentage":".667","losses":1,"ties":2,"points":11},"score":1,"is_winner":false,"linescores":[{"score":1,"period":{"id":1,"name":"1st","unit":"Half","full_name":"1st"},"shots":1},{"score":0,"period":{"id":2,"name":"2nd","unit":"Half","full_name":"2nd"},"shots":5}]}]},{"id":2161595,"event_type":{"id":"1","name":"Regular Season"},"league":{"name":"Spain Liga Primera","abbreviation":"La Liga"},"start":{"local":"2019-09-21T13:00:00","utc":"2019-09-21T11:00:00","epoch":"1569063600"},"venue":{"city":"Villarreal","venueId":5280,"name":"Estadio de la Ceramica","country":{"abbreviation":"ESP","name":"Spain"}},"status":{"name":"Final","id":4,"is_active":false},"teams":[{"id":6170,"name":"Villarreal","abbreviation":"VIL","location":{"name":"Villarreal","type":"home"},"title":"Villarreal","logo":{"base":"https://cdn-s3.si.com/s3fs-public/teams/soccer/liga/logos/","cuts":{"default":"vil_50.png","50x50":"vil_50.png","100x100":"vil_100.png","100x100_light":"vil_100_stroke.png","360x360":"vil_360.png","250x250":"vil_250.png","150x150":"vil_150.png","40x40":"vil_40.png","40x40_light":"vil_40_stroke.png"}},"color":{"primary":"#005187","secondary":"#FFE667"},"slug":"soccer/team/villarreal","record":{"wins":2,"percentage":".600","losses":1,"ties":2,"points":8},"score":2,"is_winner":true,"linescores":[{"score":0,"period":{"id":1,"name":"1st","unit":"Half","full_name":"1st"},"shots":4},{"score":2,"period":{"id":2,"name":"2nd","unit":"Half","full_name":"2nd"},"shots":14}]},{"id":"7189","name":"Valladolid","abbreviation":"REV","location":{"name":"Valladolid","type":"away"},"title":"Valladolid","logo":{"base":"https://cdn-s3.si.com/s3fs-public/teams/soccer/liga/logos/","cuts":{"default":"rev_50.png","50x50":"rev_50.png","100x100":"rev_100.png","100x100_light":"rev_100_stroke.png","360x360":"rev_360.png","250x250":"rev_250.png","150x150":"rev_150.png","40x40":"rev_40.png","40x40_light":"rev_40_stroke.png"}},"color":{"primary":"#000000","secondary":"#ffffff"},"slug":"soccer/team/valladolid","record":{"wins":1,"percentage":".400","losses":2,"ties":2,"points":5},"score":0,"is_winner":false,"linescores":[{"score":0,"period":{"id":1,"name":"1st","unit":"Half","full_name":"1st"},"shots":1},{"score":0,"period":{"id":2,"name":"2nd","unit":"Half","full_name":"2nd"},"shots":6}]}]},{"id":2161578,"event_type":{"id":"1","name":"Regular Season"},"league":{"name":"Spain Liga Primera","abbreviation":"La Liga"},"start":{"local":"2019-09-15T18:30:00","utc":"2019-09-15T16:30:00","epoch":"1568565000"},"venue":{"city":"Valladolid","venueId":5277,"name":"Jose Zorrilla","country":{"abbreviation":"ESP","name":"Spain"}},"status":{"name":"Final","id":4,"is_active":false},"teams":[{"id":7189,"name":"Valladolid","abbreviation":"REV","location":{"name":"Valladolid","type":"home"},"title":"Valladolid","logo":{"base":"https://cdn-s3.si.com/s3fs-public/teams/soccer/liga/logos/","cuts":{"default":"rev_50.png","50x50":"rev_50.png","100x100":"rev_100.png","100x100_light":"rev_100_stroke.png","360x360":"rev_360.png","250x250":"rev_250.png","150x150":"rev_150.png","40x40":"rev_40.png","40x40_light":"rev_40_stroke.png"}},"color":{"primary":"#000000","secondary":"#ffffff"},"slug":"soccer/team/valladolid","record":{"wins":1,"percentage":".500","losses":1,"ties":2,"points":5},"score":1,"is_winner":false,"linescores":[{"score":0,"period":{"id":1,"name":"1st","unit":"Half","full_name":"1st"},"shots":7},{"score":1,"period":{"id":2,"name":"2nd","unit":"Half","full_name":"2nd"},"shots":4}]},{"id":"6175","name":"Osasuna","abbreviation":"OSA","location":{"name":"Osasuna","type":"away"},"title":"Osasuna","logo":{"base":"https://cdn-s3.si.com/s3fs-public/teams/soccer/liga/logos/","cuts":{"default":"osa_50.png","50x50":"osa_50.png","100x100":"osa_100.png","100x100_light":"osa_100_stroke.png","360x360":"osa_360.png","250x250":"osa_250.png","150x150":"osa_150.png","40x40":"osa_40.png","40x40_light":"osa_40_stroke.png"}},"color":{"primary":"#000000","secondary":"#ffffff"},"slug":"soccer/team/osasuna","record":{"wins":1,"percentage":".625","losses":0,"ties":3,"points":6},"score":1,"is_winner":false,"linescores":[{"score":0,"period":{"id":1,"name":"1st","unit":"Half","full_name":"1st"},"shots":9},{"score":1,"period":{"id":2,"name":"2nd","unit":"Half","full_name":"2nd"},"shots":8}]}]},{"id":2161537,"event_type":{"id":"1","name":"Regular Season"},"league":{"name":"Spain Liga Primera","abbreviation":"La Liga"},"start":{"local":"2019-08-31T19:00:00","utc":"2019-08-31T17:00:00","epoch":"1567270800"},"venue":{"city":"Valencia","venueId":5502,"name":"Ciutat de Valencia","country":{"abbreviation":"ESP","name":"Spain"}},"status":{"name":"Final","id":4,"is_active":false},"teams":[{"id":6166,"name":"Levante","abbreviation":"LEV","location":{"name":"Levante","type":"home"},"title":"Levante","logo":{"base":"https://cdn-s3.si.com/s3fs-public/teams/soccer/liga/logos/","cuts":{"default":"lev_50.png","50x50":"lev_50.png","100x100":"lev_100.png","100x100_light":"lev_100_stroke.png","360x360":"lev_360.png","250x250":"lev_250.png","150x150":"lev_150.png","40x40":"lev_40.png","40x40_light":"lev_40_stroke.png"}},"color":{"primary":"#0E3B67","secondary":"#000000"},"slug":"soccer/team/levante","record":{"wins":2,"percentage":".667","losses":1,"ties":0,"points":6},"score":2,"is_winner":true,"linescores":[{"score":0,"period":{"id":1,"name":"1st","unit":"Half","full_name":"1st"},"shots":9},{"score":2,"period":{"id":2,"name":"2nd","unit":"Half","full_name":"2nd"},"shots":7}]},{"id":"7189","name":"Valladolid","abbreviation":"REV","location":{"name":"Valladolid","type":"away"},"title":"Valladolid","logo":{"base":"https://cdn-s3.si.com/s3fs-public/teams/soccer/liga/logos/","cuts":{"default":"rev_50.png","50x50":"rev_50.png","100x100":"rev_100.png","100x100_light":"rev_100_stroke.png","360x360":"rev_360.png","250x250":"rev_250.png","150x150":"rev_150.png","40x40":"rev_40.png","40x40_light":"rev_40_stroke.png"}},"color":{"primary":"#000000","secondary":"#ffffff"},"slug":"soccer/team/valladolid","record":{"wins":1,"percentage":".500","losses":1,"ties":1,"points":4},"score":0,"is_winner":false,"linescores":[{"score":0,"period":{"id":1,"name":"1st","unit":"Half","full_name":"1st"},"shots":6},{"score":0,"period":{"id":2,"name":"2nd","unit":"Half","full_name":"2nd"},"shots":9}]}]}],"ATL":[{"id":2161616,"event_type":{"id":"1","name":"Regular Season"},"league":{"name":"Spain Liga Primera","abbreviation":"La Liga"},"start":{"local":"2019-09-28T21:00:00","utc":"2019-09-28T19:00:00","epoch":"1569697200"},"venue":{"city":"Madrid","venueId":20323,"name":"Wanda Metropolitano","country":{"abbreviation":"ESP","name":"Spain"}},"status":{"name":"Final","id":4,"is_active":false},"teams":[{"id":6172,"name":"Atletico Madrid","abbreviation":"ATL","location":{"name":"Atletico Madrid","type":"home"},"title":"Atletico Madrid","logo":{"base":"https://cdn-s3.si.com/s3fs-public/teams/soccer/liga/logos/","cuts":{"default":"atl_50.png","50x50":"atl_50.png","100x100":"atl_100.png","100x100_light":"atl_100_stroke.png","360x360":"atl_360.png","250x250":"atl_250.png","150x150":"atl_150.png","40x40":"atl_40.png","40x40_light":"atl_40_stroke.png"}},"color":{"primary":"#13007C","secondary":"#FF0D00"},"slug":"soccer/team/atletico-madrid","record":{"wins":4,"percentage":".714","losses":1,"ties":2,"points":14},"score":0,"is_winner":false,"linescores":[{"score":0,"period":{"id":1,"name":"1st","unit":"Half","full_name":"1st"},"shots":3},{"score":0,"period":{"id":2,"name":"2nd","unit":"Half","full_name":"2nd"},"shots":4}]},{"id":"6171","name":"Real Madrid","abbreviation":"RMD","location":{"name":"Real Madrid","type":"away"},"title":"Real Madrid","logo":{"base":"https://cdn-s3.si.com/s3fs-public/teams/soccer/liga/logos/","cuts":{"default":"rmd_50.png","50x50":"rmd_50.png","100x100":"rmd_100.png","100x100_light":"rmd_100_stroke.png","360x360":"rmd_360.png","250x250":"rmd_250.png","150x150":"rmd_150.png","40x40":"rmd_40.png","40x40_light":"rmd_40_stroke.png"}},"color":{"primary":"#00529F","secondary":"#FEBE10"},"slug":"soccer/team/real-madrid","record":{"wins":4,"percentage":".786","losses":0,"ties":3,"points":15},"score":0,"is_winner":false,"linescores":[{"score":0,"period":{"id":1,"name":"1st","unit":"Half","full_name":"1st"},"shots":7},{"score":0,"period":{"id":2,"name":"2nd","unit":"Half","full_name":"2nd"},"shots":7}]}]},{"id":2161605,"event_type":{"id":"1","name":"Regular Season"},"league":{"name":"Spain Liga Primera","abbreviation":"La Liga"},"start":{"local":"2019-09-25T19:00:00","utc":"2019-09-25T17:00:00","epoch":"1569430800"},"venue":{"city":"Palma de Mallorca","venueId":5271,"name":"Son Moix","country":{"abbreviation":"ESP","name":"Spain"}},"status":{"name":"Final","id":4,"is_active":false},"teams":[{"id":6176,"name":"Mallorca","abbreviation":"MRC","location":{"name":"Mallorca","type":"home"},"title":"Mallorca","logo":{"base":"https://cdn-s3.si.com/s3fs-public/teams/soccer/liga/logos/","cuts":{"default":"mrc_50.png","50x50":"mrc_50.png","100x100":"mrc_100.png","100x100_light":"mrc_100_stroke.png","360x360":"mrc_360.png","250x250":"mrc_250.png","150x150":"mrc_150.png","40x40":"mrc_40.png","40x40_light":"mrc_40_stroke.png"}},"color":{"primary":"#000000","secondary":"#ffffff"},"slug":"soccer/team/mallorca","record":{"wins":1,"percentage":".250","losses":4,"ties":1,"points":4},"score":0,"is_winner":false,"linescores":[{"score":0,"period":{"id":1,"name":"1st","unit":"Half","full_name":"1st"},"shots":2},{"score":0,"period":{"id":2,"name":"2nd","unit":"Half","full_name":"2nd"},"shots":7}]},{"id":"6172","name":"Atletico Madrid","abbreviation":"ATL","location":{"name":"Atletico Madrid","type":"away"},"title":"Atletico Madrid","logo":{"base":"https://cdn-s3.si.com/s3fs-public/teams/soccer/liga/logos/","cuts":{"default":"atl_50.png","50x50":"atl_50.png","100x100":"atl_100.png","100x100_light":"atl_100_stroke.png","360x360":"atl_360.png","250x250":"atl_250.png","150x150":"atl_150.png","40x40":"atl_40.png","40x40_light":"atl_40_stroke.png"}},"color":{"primary":"#13007C","secondary":"#FF0D00"},"slug":"soccer/team/atletico-madrid","record":{"wins":4,"percentage":".750","losses":1,"ties":1,"points":13},"score":2,"is_winner":true,"linescores":[{"score":1,"period":{"id":1,"name":"1st","unit":"Half","full_name":"1st"},"shots":9},{"score":1,"period":{"id":2,"name":"2nd","unit":"Half","full_name":"2nd"},"shots":4}]}]},{"id":2161581,"event_type":{"id":"1","name":"Regular Season"},"league":{"name":"Spain Liga Primera","abbreviation":"La Liga"},"start":{"local":"2019-09-21T18:30:00","utc":"2019-09-21T16:30:00","epoch":"1569083400"},"venue":{"city":"Madrid","venueId":20323,"name":"Wanda Metropolitano","country":{"abbreviation":"ESP","name":"Spain"}},"status":{"name":"Final","id":4,"is_active":false},"teams":[{"id":6172,"name":"Atletico Madrid","abbreviation":"ATL","location":{"name":"Atletico Madrid","type":"home"},"title":"Atletico Madrid","logo":{"base":"https://cdn-s3.si.com/s3fs-public/teams/soccer/liga/logos/","cuts":{"default":"atl_50.png","50x50":"atl_50.png","100x100":"atl_100.png","100x100_light":"atl_100_stroke.png","360x360":"atl_360.png","250x250":"atl_250.png","150x150":"atl_150.png","40x40":"atl_40.png","40x40_light":"atl_40_stroke.png"}},"color":{"primary":"#13007C","secondary":"#FF0D00"},"slug":"soccer/team/atletico-madrid","record":{"wins":3,"percentage":".700","losses":1,"ties":1,"points":10},"score":0,"is_winner":false,"linescores":[{"score":0,"period":{"id":1,"name":"1st","unit":"Half","full_name":"1st"},"shots":10},{"score":0,"period":{"id":2,"name":"2nd","unit":"Half","full_name":"2nd"},"shots":10}]},{"id":"6163","name":"Celta Vigo","abbreviation":"CEL","location":{"name":"Celta Vigo","type":"away"},"title":"Celta Vigo","logo":{"base":"https://cdn-s3.si.com/s3fs-public/teams/soccer/liga/logos/","cuts":{"default":"cel_50.png","50x50":"cel_50.png","100x100":"cel_100.png","100x100_light":"cel_100_stroke.png","360x360":"cel_360.png","250x250":"cel_250.png","150x150":"cel_150.png","40x40":"cel_40.png","40x40_light":"cel_40_stroke.png"}},"color":{"primary":"#000000","secondary":"#8AC3EE"},"slug":"soccer/team/celta-vigo","record":{"wins":1,"percentage":".400","losses":2,"ties":2,"points":5},"score":0,"is_winner":false,"linescores":[{"score":0,"period":{"id":1,"name":"1st","unit":"Half","full_name":"1st"},"shots":2},{"score":0,"period":{"id":2,"name":"2nd","unit":"Half","full_name":"2nd"},"shots":4}]}]},{"id":2161576,"event_type":{"id":"1","name":"Regular Season"},"league":{"name":"Spain Liga Primera","abbreviation":"La Liga"},"start":{"local":"2019-09-14T18:30:00","utc":"2019-09-14T16:30:00","epoch":"1568478600"},"venue":{"city":"San Sebastian","venueId":5269,"name":"Anoeta","country":{"abbreviation":"ESP","name":"Spain"}},"status":{"name":"Final","id":4,"is_active":false},"teams":[{"id":6160,"name":"Real Sociedad","abbreviation":"RSO","location":{"name":"Real Sociedad","type":"home"},"title":"Real Sociedad","logo":{"base":"https://cdn-s3.si.com/s3fs-public/teams/soccer/liga/logos/","cuts":{"default":"rso_50.png","50x50":"rso_50.png","100x100":"rso_100.png","100x100_light":"rso_100_stroke.png","360x360":"rso_360.png","250x250":"rso_250.png","150x150":"rso_150.png","40x40":"rso_40.png","40x40_light":"rso_40_stroke.png"}},"color":{"primary":"#143C8B","secondary":"#000000"},"slug":"soccer/team/real-sociedad","record":{"wins":2,"percentage":".625","losses":1,"ties":1,"points":7},"score":2,"is_winner":true,"linescores":[{"score":0,"period":{"id":1,"name":"1st","unit":"Half","full_name":"1st"},"shots":7},{"score":2,"period":{"id":2,"name":"2nd","unit":"Half","full_name":"2nd"},"shots":6}]},{"id":"6172","name":"Atletico Madrid","abbreviation":"ATL","location":{"name":"Atletico Madrid","type":"away"},"title":"Atletico Madrid","logo":{"base":"https://cdn-s3.si.com/s3fs-public/teams/soccer/liga/logos/","cuts":{"default":"atl_50.png","50x50":"atl_50.png","100x100":"atl_100.png","100x100_light":"atl_100_stroke.png","360x360":"atl_360.png","250x250":"atl_250.png","150x150":"atl_150.png","40x40":"atl_40.png","40x40_light":"atl_40_stroke.png"}},"color":{"primary":"#13007C","secondary":"#FF0D00"},"slug":"soccer/team/atletico-madrid","record":{"wins":3,"percentage":".750","losses":1,"ties":0,"points":9},"score":0,"is_winner":false,"linescores":[{"score":0,"period":{"id":1,"name":"1st","unit":"Half","full_name":"1st"},"shots":4},{"score":0,"period":{"id":2,"name":"2nd","unit":"Half","full_name":"2nd"},"shots":8}]}]},{"id":2161519,"event_type":{"id":"1","name":"Regular Season"},"league":{"name":"Spain Liga Primera","abbreviation":"La Liga"},"start":{"local":"2019-09-01T19:00:00","utc":"2019-09-01T17:00:00","epoch":"1567357200"},"venue":{"city":"Madrid","venueId":20323,"name":"Wanda Metropolitano","country":{"abbreviation":"ESP","name":"Spain"}},"status":{"name":"Final","id":4,"is_active":false},"teams":[{"id":6172,"name":"Atletico Madrid","abbreviation":"ATL","location":{"name":"Atletico Madrid","type":"home"},"title":"Atletico Madrid","logo":{"base":"https://cdn-s3.si.com/s3fs-public/teams/soccer/liga/logos/","cuts":{"default":"atl_50.png","50x50":"atl_50.png","100x100":"atl_100.png","100x100_light":"atl_100_stroke.png","360x360":"atl_360.png","250x250":"atl_250.png","150x150":"atl_150.png","40x40":"atl_40.png","40x40_light":"atl_40_stroke.png"}},"color":{"primary":"#13007C","secondary":"#FF0D00"},"slug":"soccer/team/atletico-madrid","record":{"wins":3,"percentage":"1.000","losses":0,"ties":0,"points":9},"score":3,"is_winner":true,"linescores":[{"score":1,"period":{"id":1,"name":"1st","unit":"Half","full_name":"1st"},"shots":2},{"score":2,"period":{"id":2,"name":"2nd","unit":"Half","full_name":"2nd"},"shots":5}]},{"id":"8319","name":"Eibar","abbreviation":"EIB","location":{"name":"Eibar","type":"away"},"title":"Eibar","logo":{"base":"https://cdn-s3.si.com/s3fs-public/teams/soccer/liga/logos/","cuts":{"default":"eib_50.png","50x50":"eib_50.png","100x100":"eib_100.png","100x100_light":"eib_100_stroke.png","360x360":"eib_360.png","250x250":"eib_250.png","150x150":"eib_150.png","40x40":"eib_40.png","40x40_light":"eib_40_stroke.png"}},"color":{"primary":"#0071B9","secondary":"#1C2F6D"},"slug":"soccer/team/eibar","record":{"wins":0,"percentage":".167","losses":2,"ties":1,"points":1},"score":2,"is_winner":false,"linescores":[{"score":2,"period":{"id":1,"name":"1st","unit":"Half","full_name":"1st"},"shots":3},{"score":0,"period":{"id":2,"name":"2nd","unit":"Half","full_name":"2nd"},"shots":3}]}]}]},"head_to_head":[{"id":2069329,"event_type":{"id":"1","name":"Regular Season"},"league":{"name":"Spain Liga Primera","abbreviation":"La Liga"},"start":{"local":"2019-04-27T16:15:00","utc":"2019-04-27T14:15:00","epoch":"1556374500"},"venue":{"city":"Madrid","venueId":20323,"name":"Wanda Metropolitano","country":{"abbreviation":"ESP","name":"Spain"}},"status":{"name":"Final","id":4,"is_active":false},"teams":[{"id":6172,"name":"Atletico Madrid","abbreviation":"ATL","location":{"name":"Atletico Madrid","type":"home"},"title":"Atletico Madrid","logo":{"base":"https://cdn-s3.si.com/s3fs-public/teams/soccer/liga/logos/","cuts":{"default":"atl_50.png","50x50":"atl_50.png","100x100":"atl_100.png","100x100_light":"atl_100_stroke.png","360x360":"atl_360.png","250x250":"atl_250.png","150x150":"atl_150.png","40x40":"atl_40.png","40x40_light":"atl_40_stroke.png"}},"color":{"primary":"#13007C","secondary":"#FF0D00"},"slug":"soccer/team/atletico-madrid","record":{"wins":22,"percentage":".743","losses":5,"ties":8,"points":74},"score":1,"is_winner":true,"linescores":[{"score":0,"period":{"id":1,"name":"1st","unit":"Half","full_name":"1st"},"shots":7},{"score":1,"period":{"id":2,"name":"2nd","unit":"Half","full_name":"2nd"},"shots":6}]},{"id":"7189","name":"Valladolid","abbreviation":"REV","location":{"name":"Valladolid","type":"away"},"title":"Valladolid","logo":{"base":"https://cdn-s3.si.com/s3fs-public/teams/soccer/liga/logos/","cuts":{"default":"rev_50.png","50x50":"rev_50.png","100x100":"rev_100.png","100x100_light":"rev_100_stroke.png","360x360":"rev_360.png","250x250":"rev_250.png","150x150":"rev_150.png","40x40":"rev_40.png","40x40_light":"rev_40_stroke.png"}},"color":{"primary":"#000000","secondary":"#ffffff"},"slug":"soccer/team/valladolid","record":{"wins":8,"percentage":".386","losses":16,"ties":11,"points":35},"score":0,"is_winner":false,"linescores":[{"score":0,"period":{"id":1,"name":"1st","unit":"Half","full_name":"1st"},"shots":2},{"score":0,"period":{"id":2,"name":"2nd","unit":"Half","full_name":"2nd"},"shots":11}]}]},{"id":2069221,"event_type":{"id":"1","name":"Regular Season"},"league":{"name":"Spain Liga Primera","abbreviation":"La Liga"},"start":{"local":"2018-12-15T16:15:00","utc":"2018-12-15T15:15:00","epoch":"1544886900"},"venue":{"city":"Valladolid","venueId":5277,"name":"Jose Zorrilla","country":{"abbreviation":"ESP","name":"Spain"}},"status":{"name":"Final","id":4,"is_active":false},"teams":[{"id":7189,"name":"Valladolid","abbreviation":"REV","location":{"name":"Valladolid","type":"home"},"title":"Valladolid","logo":{"base":"https://cdn-s3.si.com/s3fs-public/teams/soccer/liga/logos/","cuts":{"default":"rev_50.png","50x50":"rev_50.png","100x100":"rev_100.png","100x100_light":"rev_100_stroke.png","360x360":"rev_360.png","250x250":"rev_250.png","150x150":"rev_150.png","40x40":"rev_40.png","40x40_light":"rev_40_stroke.png"}},"color":{"primary":"#000000","secondary":"#ffffff"},"slug":"soccer/team/valladolid","record":{"wins":5,"percentage":".469","losses":6,"ties":5,"points":20},"score":2,"is_winner":false,"linescores":[{"score":0,"period":{"id":1,"name":"1st","unit":"Half","full_name":"1st"},"shots":3},{"score":2,"period":{"id":2,"name":"2nd","unit":"Half","full_name":"2nd"},"shots":5}]},{"id":"6172","name":"Atletico Madrid","abbreviation":"ATL","location":{"name":"Atletico Madrid","type":"away"},"title":"Atletico Madrid","logo":{"base":"https://cdn-s3.si.com/s3fs-public/teams/soccer/liga/logos/","cuts":{"default":"atl_50.png","50x50":"atl_50.png","100x100":"atl_100.png","100x100_light":"atl_100_stroke.png","360x360":"atl_360.png","250x250":"atl_250.png","150x150":"atl_150.png","40x40":"atl_40.png","40x40_light":"atl_40_stroke.png"}},"color":{"primary":"#13007C","secondary":"#FF0D00"},"slug":"soccer/team/atletico-madrid","record":{"wins":8,"percentage":".719","losses":1,"ties":7,"points":31},"score":3,"is_winner":true,"linescores":[{"score":2,"period":{"id":1,"name":"1st","unit":"Half","full_name":"1st"},"shots":6},{"score":1,"period":{"id":2,"name":"2nd","unit":"Half","full_name":"2nd"},"shots":8}]}]}],"editorial":{"has_preview":false,"has_recap":false,"has_bullets":false,"has_odds":false}}}